{
	"configurations" : 
	[
		{
			"directories" : 
			[
				{
					"build" : ".",
					"jsonFile" : "directory-.-Debug-f5ebdc15457944623624.json",
					"minimumCMakeVersion" : 
					{
						"string" : "3.29"
					},
					"projectIndex" : 0,
					"source" : ".",
					"targetIndexes" : 
					[
						0
					]
				}
			],
			"name" : "Debug",
			"projects" : 
			[
				{
					"directoryIndexes" : 
					[
						0
					],
					"name" : "test",
					"targetIndexes" : 
					[
						0
					]
				}
			],
			"targets" : 
			[
				{
					"directoryIndex" : 0,
					"id" : "test::@6890427a1f51a3e7e1df",
					"jsonFile" : "target-test-Debug-4e021b8556ebc0dd2783.json",
					"name" : "test",
					"projectIndex" : 0
				}
			]
		}
	],
	"kind" : "codemodel",
	"paths" : 
	{
		"build" : "/Users/enushkevich/programming/C++/test/cmake-build-debug",
		"source" : "/Users/enushkevich/programming/C++/test"
	},
	"version" : 
	{
		"major" : 2,
		"minor" : 7
	}
}
